{
  "typography": {
    "title": {
      "h2": {
        "value": {
          "font": {
            "type": "font",
            "value": {
              "family": {
                "type": "string",
                "value": "Plus Jakarta Sans"
              },
              "subfamily": {
                "type": "string",
                "value": "SemiBold"
              }
            }
          },
          "fontSize": {
            "type": "measure",
            "value": "{measure.dimension.typography.font-size.20.value}"
          },
          "textDecoration": "None",
          "textCase": "Original",
          "letterSpacing": {
            "type": "measure",
            "value": {
              "measure": {
                "type": "size",
                "value": 0.4000000059604645
              },
              "unit": {
                "type": "string",
                "value": "pixels"
              }
            }
          },
          "paragraphIndent": {
            "type": "measure",
            "value": {
              "measure": {
                "type": "size",
                "value": 0
              },
              "unit": {
                "type": "string",
                "value": "pixels"
              }
            }
          },
          "lineHeight": {
            "type": "measure",
            "value": "{measure.dimension.typography.line-height.26.value}"
          }
        },
        "type": "typography"
      },
      "h3": {
        "value": {
          "font": {
            "type": "font",
            "value": {
              "family": {
                "type": "string",
                "value": "Plus Jakarta Sans"
              },
              "subfamily": {
                "type": "string",
                "value": "Regular"
              }
            }
          },
          "fontSize": {
            "type": "measure",
            "value": "{measure.dimension.typography.font-size.18.value}"
          },
          "textDecoration": "None",
          "textCase": "Original",
          "letterSpacing": {
            "type": "measure",
            "value": {
              "measure": {
                "type": "size",
                "value": 0
              },
              "unit": {
                "type": "string",
                "value": "pixels"
              }
            }
          },
          "paragraphIndent": {
            "type": "measure",
            "value": {
              "measure": {
                "type": "size",
                "value": 0
              },
              "unit": {
                "type": "string",
                "value": "pixels"
              }
            }
          },
          "lineHeight": {
            "type": "measure",
            "value": "{measure.dimension.typography.line-height.22.value}"
          }
        },
        "type": "typography"
      },
      "h0": {
        "value": {
          "font": {
            "type": "font",
            "value": {
              "family": {
                "type": "string",
                "value": "Plus Jakarta Sans"
              },
              "subfamily": {
                "type": "string",
                "value": "SemiBold"
              }
            }
          },
          "fontSize": {
            "type": "measure",
            "value": "{measure.dimension.typography.font-size.40.value}"
          },
          "textDecoration": "None",
          "textCase": "Original",
          "letterSpacing": {
            "type": "measure",
            "value": {
              "measure": {
                "type": "size",
                "value": 0
              },
              "unit": {
                "type": "string",
                "value": "pixels"
              }
            }
          },
          "paragraphIndent": {
            "type": "measure",
            "value": {
              "measure": {
                "type": "size",
                "value": 0
              },
              "unit": {
                "type": "string",
                "value": "pixels"
              }
            }
          },
          "lineHeight": {
            "type": "measure",
            "value": "{measure.dimension.typography.line-height.46.value}"
          }
        },
        "type": "typography"
      },
      "h1": {
        "value": {
          "font": {
            "type": "font",
            "value": {
              "family": {
                "type": "string",
                "value": "Plus Jakarta Sans"
              },
              "subfamily": {
                "type": "string",
                "value": "SemiBold"
              }
            }
          },
          "fontSize": {
            "type": "measure",
            "value": "{measure.dimension.typography.font-size.30.value}"
          },
          "textDecoration": "None",
          "textCase": "Original",
          "letterSpacing": {
            "type": "measure",
            "value": {
              "measure": {
                "type": "size",
                "value": 0.4000000059604645
              },
              "unit": {
                "type": "string",
                "value": "pixels"
              }
            }
          },
          "paragraphIndent": {
            "type": "measure",
            "value": {
              "measure": {
                "type": "size",
                "value": 0
              },
              "unit": {
                "type": "string",
                "value": "pixels"
              }
            }
          },
          "lineHeight": {
            "type": "measure",
            "value": "{measure.dimension.typography.line-height.36.value}"
          }
        },
        "type": "typography"
      },
      "h4": {
        "value": {
          "font": {
            "type": "font",
            "value": {
              "family": {
                "type": "string",
                "value": "Plus Jakarta Sans"
              },
              "subfamily": {
                "type": "string",
                "value": "SemiBold"
              }
            }
          },
          "fontSize": {
            "type": "measure",
            "value": "{measure.dimension.typography.font-size.14.value}"
          },
          "textDecoration": "None",
          "textCase": "Original",
          "letterSpacing": {
            "type": "measure",
            "value": {
              "measure": {
                "type": "size",
                "value": 0
              },
              "unit": {
                "type": "string",
                "value": "pixels"
              }
            }
          },
          "paragraphIndent": {
            "type": "measure",
            "value": {
              "measure": {
                "type": "size",
                "value": 0
              },
              "unit": {
                "type": "string",
                "value": "pixels"
              }
            }
          },
          "lineHeight": {
            "type": "measure",
            "value": "{measure.dimension.typography.line-height.18.value}"
          }
        },
        "type": "typography"
      },
      "h5": {
        "value": {
          "font": {
            "type": "font",
            "value": {
              "family": {
                "type": "string",
                "value": "Plus Jakarta Sans"
              },
              "subfamily": {
                "type": "string",
                "value": "SemiBold"
              }
            }
          },
          "fontSize": {
            "type": "measure",
            "value": "{measure.dimension.typography.font-size.12.value}"
          },
          "textDecoration": "None",
          "textCase": "Original",
          "letterSpacing": {
            "type": "measure",
            "value": {
              "measure": {
                "type": "size",
                "value": 0.4000000059604645
              },
              "unit": {
                "type": "string",
                "value": "pixels"
              }
            }
          },
          "paragraphIndent": {
            "type": "measure",
            "value": {
              "measure": {
                "type": "size",
                "value": 0
              },
              "unit": {
                "type": "string",
                "value": "pixels"
              }
            }
          },
          "lineHeight": {
            "type": "measure",
            "value": "{measure.dimension.typography.line-height.18.value}"
          }
        },
        "type": "typography"
      },
      "h6": {
        "value": {
          "font": {
            "type": "font",
            "value": {
              "family": {
                "type": "string",
                "value": "Plus Jakarta Sans"
              },
              "subfamily": {
                "type": "string",
                "value": "SemiBold"
              }
            }
          },
          "fontSize": {
            "type": "measure",
            "value": "{measure.dimension.typography.font-size.10.value}"
          },
          "textDecoration": "None",
          "textCase": "Original",
          "letterSpacing": {
            "type": "measure",
            "value": {
              "measure": {
                "type": "size",
                "value": 0.4000000059604645
              },
              "unit": {
                "type": "string",
                "value": "pixels"
              }
            }
          },
          "paragraphIndent": {
            "type": "measure",
            "value": {
              "measure": {
                "type": "size",
                "value": 0
              },
              "unit": {
                "type": "string",
                "value": "pixels"
              }
            }
          },
          "lineHeight": {
            "type": "measure",
            "value": "{measure.dimension.typography.line-height.16.value}"
          }
        },
        "type": "typography"
      }
    },
    "higlight-numbers": {
      "n1": {
        "value": {
          "font": {
            "type": "font",
            "value": {
              "family": {
                "type": "string",
                "value": "Plus Jakarta Sans"
              },
              "subfamily": {
                "type": "string",
                "value": "Medium"
              }
            }
          },
          "fontSize": {
            "type": "measure",
            "value": "{measure.dimension.typography.font-size.45.value}"
          },
          "textDecoration": "None",
          "textCase": "Original",
          "letterSpacing": {
            "type": "measure",
            "value": {
              "measure": {
                "type": "size",
                "value": 0
              },
              "unit": {
                "type": "string",
                "value": "pixels"
              }
            }
          },
          "paragraphIndent": {
            "type": "measure",
            "value": {
              "measure": {
                "type": "size",
                "value": 0
              },
              "unit": {
                "type": "string",
                "value": "pixels"
              }
            }
          },
          "lineHeight": {
            "type": "measure",
            "value": "{measure.dimension.typography.line-height.51.value}"
          }
        },
        "type": "typography"
      },
      "n2": {
        "value": {
          "font": {
            "type": "font",
            "value": {
              "family": {
                "type": "string",
                "value": "Plus Jakarta Sans"
              },
              "subfamily": {
                "type": "string",
                "value": "Bold"
              }
            }
          },
          "fontSize": {
            "type": "measure",
            "value": "{measure.dimension.typography.font-size.22.value}"
          },
          "textDecoration": "None",
          "textCase": "Original",
          "letterSpacing": {
            "type": "measure",
            "value": {
              "measure": {
                "type": "size",
                "value": 0
              },
              "unit": {
                "type": "string",
                "value": "pixels"
              }
            }
          },
          "paragraphIndent": {
            "type": "measure",
            "value": {
              "measure": {
                "type": "size",
                "value": 0
              },
              "unit": {
                "type": "string",
                "value": "pixels"
              }
            }
          },
          "lineHeight": {
            "type": "measure",
            "value": "{measure.dimension.typography.line-height.28.value}"
          }
        },
        "type": "typography"
      },
      "n3": {
        "value": {
          "font": {
            "type": "font",
            "value": {
              "family": {
                "type": "string",
                "value": "Plus Jakarta Sans"
              },
              "subfamily": {
                "type": "string",
                "value": "Regular"
              }
            }
          },
          "fontSize": {
            "type": "measure",
            "value": "{measure.dimension.typography.font-size.20.value}"
          },
          "textDecoration": "None",
          "textCase": "Original",
          "letterSpacing": {
            "type": "measure",
            "value": {
              "measure": {
                "type": "size",
                "value": 0
              },
              "unit": {
                "type": "string",
                "value": "pixels"
              }
            }
          },
          "paragraphIndent": {
            "type": "measure",
            "value": {
              "measure": {
                "type": "size",
                "value": 0
              },
              "unit": {
                "type": "string",
                "value": "pixels"
              }
            }
          },
          "lineHeight": {
            "type": "measure",
            "value": "{measure.dimension.typography.line-height.26.value}"
          }
        },
        "type": "typography"
      },
      "n4": {
        "value": {
          "font": {
            "type": "font",
            "value": {
              "family": {
                "type": "string",
                "value": "Plus Jakarta Sans"
              },
              "subfamily": {
                "type": "string",
                "value": "SemiBold"
              }
            }
          },
          "fontSize": {
            "type": "measure",
            "value": "{measure.dimension.typography.font-size.12.value}"
          },
          "textDecoration": "None",
          "textCase": "Original",
          "letterSpacing": {
            "type": "measure",
            "value": {
              "measure": {
                "type": "size",
                "value": 0.4000000059604645
              },
              "unit": {
                "type": "string",
                "value": "pixels"
              }
            }
          },
          "paragraphIndent": {
            "type": "measure",
            "value": {
              "measure": {
                "type": "size",
                "value": 0
              },
              "unit": {
                "type": "string",
                "value": "pixels"
              }
            }
          },
          "lineHeight": {
            "type": "measure",
            "value": "{measure.dimension.typography.line-height.18.value}"
          }
        },
        "type": "typography"
      }
    },
    "body": {
      "b3": {
        "value": {
          "font": {
            "type": "font",
            "value": {
              "family": {
                "type": "string",
                "value": "Plus Jakarta Sans"
              },
              "subfamily": {
                "type": "string",
                "value": "Regular"
              }
            }
          },
          "fontSize": {
            "type": "measure",
            "value": "{measure.dimension.typography.font-size.12.value}"
          },
          "textDecoration": "None",
          "textCase": "Original",
          "letterSpacing": {
            "type": "measure",
            "value": {
              "measure": {
                "type": "size",
                "value": 0.4000000059604645
              },
              "unit": {
                "type": "string",
                "value": "pixels"
              }
            }
          },
          "paragraphIndent": {
            "type": "measure",
            "value": {
              "measure": {
                "type": "size",
                "value": 0
              },
              "unit": {
                "type": "string",
                "value": "pixels"
              }
            }
          },
          "lineHeight": {
            "type": "measure",
            "value": "{measure.dimension.typography.line-height.16.value}"
          }
        },
        "type": "typography"
      },
      "b4": {
        "value": {
          "font": {
            "type": "font",
            "value": {
              "family": {
                "type": "string",
                "value": "Plus Jakarta Sans"
              },
              "subfamily": {
                "type": "string",
                "value": "Regular"
              }
            }
          },
          "fontSize": {
            "type": "measure",
            "value": "{measure.dimension.typography.font-size.10.value}"
          },
          "textDecoration": "None",
          "textCase": "Original",
          "letterSpacing": {
            "type": "measure",
            "value": {
              "measure": {
                "type": "size",
                "value": 0
              },
              "unit": {
                "type": "string",
                "value": "pixels"
              }
            }
          },
          "paragraphIndent": {
            "type": "measure",
            "value": {
              "measure": {
                "type": "size",
                "value": 0
              },
              "unit": {
                "type": "string",
                "value": "pixels"
              }
            }
          },
          "lineHeight": {
            "type": "measure",
            "value": "{measure.dimension.typography.line-height.14.value}"
          }
        },
        "type": "typography"
      },
      "b1": {
        "value": {
          "font": {
            "type": "font",
            "value": {
              "family": {
                "type": "string",
                "value": "Plus Jakarta Sans"
              },
              "subfamily": {
                "type": "string",
                "value": "Medium"
              }
            }
          },
          "fontSize": {
            "type": "measure",
            "value": "{measure.dimension.typography.font-size.16.value}"
          },
          "textDecoration": "None",
          "textCase": "Original",
          "letterSpacing": {
            "type": "measure",
            "value": {
              "measure": {
                "type": "size",
                "value": 0
              },
              "unit": {
                "type": "string",
                "value": "pixels"
              }
            }
          },
          "paragraphIndent": {
            "type": "measure",
            "value": {
              "measure": {
                "type": "size",
                "value": 0
              },
              "unit": {
                "type": "string",
                "value": "pixels"
              }
            }
          },
          "lineHeight": {
            "type": "measure",
            "value": "{measure.dimension.typography.line-height.20.value}"
          }
        },
        "type": "typography"
      },
      "b2": {
        "value": {
          "font": {
            "type": "font",
            "value": {
              "family": {
                "type": "string",
                "value": "Plus Jakarta Sans"
              },
              "subfamily": {
                "type": "string",
                "value": "Regular"
              }
            }
          },
          "fontSize": {
            "type": "measure",
            "value": "{measure.dimension.typography.font-size.14.value}"
          },
          "textDecoration": "None",
          "textCase": "Original",
          "letterSpacing": {
            "type": "measure",
            "value": {
              "measure": {
                "type": "size",
                "value": 0.4000000059604645
              },
              "unit": {
                "type": "string",
                "value": "pixels"
              }
            }
          },
          "paragraphIndent": {
            "type": "measure",
            "value": {
              "measure": {
                "type": "size",
                "value": 0
              },
              "unit": {
                "type": "string",
                "value": "pixels"
              }
            }
          },
          "lineHeight": {
            "type": "measure",
            "value": "{measure.dimension.typography.line-height.20.value}"
          }
        },
        "type": "typography"
      }
    },
    "others": {
      "link": {
        "default": {
          "value": {
            "font": {
              "type": "font",
              "value": {
                "family": {
                  "type": "string",
                  "value": "Plus Jakarta Sans"
                },
                "subfamily": {
                  "type": "string",
                  "value": "Regular"
                }
              }
            },
            "fontSize": {
              "type": "measure",
              "value": "{measure.dimension.typography.font-size.12.value}"
            },
            "textDecoration": "None",
            "textCase": "Original",
            "letterSpacing": {
              "type": "measure",
              "value": {
                "measure": {
                  "type": "size",
                  "value": 0
                },
                "unit": {
                  "type": "string",
                  "value": "pixels"
                }
              }
            },
            "paragraphIndent": {
              "type": "measure",
              "value": {
                "measure": {
                  "type": "size",
                  "value": 0
                },
                "unit": {
                  "type": "string",
                  "value": "pixels"
                }
              }
            },
            "lineHeight": {
              "type": "measure",
              "value": "{measure.dimension.typography.line-height.18.value}"
            }
          },
          "type": "typography"
        },
        "small": {
          "value": {
            "font": {
              "type": "font",
              "value": {
                "family": {
                  "type": "string",
                  "value": "Plus Jakarta Sans"
                },
                "subfamily": {
                  "type": "string",
                  "value": "Regular"
                }
              }
            },
            "fontSize": {
              "type": "measure",
              "value": "{measure.dimension.typography.font-size.10.value}"
            },
            "textDecoration": "None",
            "textCase": "Original",
            "letterSpacing": {
              "type": "measure",
              "value": {
                "measure": {
                  "type": "size",
                  "value": 0
                },
                "unit": {
                  "type": "string",
                  "value": "pixels"
                }
              }
            },
            "paragraphIndent": {
              "type": "measure",
              "value": {
                "measure": {
                  "type": "size",
                  "value": 0
                },
                "unit": {
                  "type": "string",
                  "value": "pixels"
                }
              }
            },
            "lineHeight": {
              "type": "measure",
              "value": "{measure.dimension.typography.line-height.16.value}"
            }
          },
          "type": "typography"
        }
      },
      "sidebar-eb": {
        "value": {
          "font": {
            "type": "font",
            "value": {
              "family": {
                "type": "string",
                "value": "Plus Jakarta Sans"
              },
              "subfamily": {
                "type": "string",
                "value": "800"
              }
            }
          },
          "fontSize": {
            "type": "measure",
            "value": "{measure.dimension.typography.font-size.20.value}"
          },
          "textDecoration": "None",
          "textCase": "Original",
          "letterSpacing": {
            "type": "measure",
            "value": {
              "measure": {
                "type": "size",
                "value": -0.25
              },
              "unit": {
                "type": "string",
                "value": "pixels"
              }
            }
          },
          "paragraphIndent": {
            "type": "measure",
            "value": {
              "measure": {
                "type": "size",
                "value": 0
              },
              "unit": {
                "type": "string",
                "value": "pixels"
              }
            }
          },
          "lineHeight": {
            "type": "measure",
            "value": "{measure.dimension.typography.line-height.26.value}"
          }
        },
        "type": "typography"
      },
      "graphs-data": {
        "value": {
          "font": {
            "type": "font",
            "value": {
              "family": {
                "type": "string",
                "value": "Plus Jakarta Sans"
              },
              "subfamily": {
                "type": "string",
                "value": "Regular"
              }
            }
          },
          "fontSize": {
            "type": "measure",
            "value": "{measure.dimension.typography.font-size.8.value}"
          },
          "textDecoration": "None",
          "textCase": "Original",
          "letterSpacing": {
            "type": "measure",
            "value": {
              "measure": {
                "type": "size",
                "value": 0.4000000059604645
              },
              "unit": {
                "type": "string",
                "value": "pixels"
              }
            }
          },
          "paragraphIndent": {
            "type": "measure",
            "value": {
              "measure": {
                "type": "size",
                "value": 0
              },
              "unit": {
                "type": "string",
                "value": "pixels"
              }
            }
          },
          "lineHeight": {
            "type": "measure",
            "value": "{measure.dimension.typography.line-height.14.value}"
          }
        },
        "type": "typography"
      },
      "small-data": {
        "value": {
          "font": {
            "type": "font",
            "value": {
              "family": {
                "type": "string",
                "value": "Plus Jakarta Sans"
              },
              "subfamily": {
                "type": "string",
                "value": "SemiBold"
              }
            }
          },
          "fontSize": {
            "type": "measure",
            "value": "{measure.dimension.typography.font-size.8.value}"
          },
          "textDecoration": "None",
          "textCase": "Original",
          "letterSpacing": {
            "type": "measure",
            "value": {
              "measure": {
                "type": "size",
                "value": 0.4000000059604645
              },
              "unit": {
                "type": "string",
                "value": "pixels"
              }
            }
          },
          "paragraphIndent": {
            "type": "measure",
            "value": {
              "measure": {
                "type": "size",
                "value": 0
              },
              "unit": {
                "type": "string",
                "value": "pixels"
              }
            }
          },
          "lineHeight": {
            "type": "measure",
            "value": "{measure.dimension.typography.line-height.16.value}"
          }
        },
        "type": "typography"
      }
    }
  }
}
